mutablesecurity/__init__.py
mutablesecurity/autodoc/__init__.py
mutablesecurity/autodoc/badges.py
mutablesecurity/autodoc/solution_spec_sheet.py
mutablesecurity/autodoc/solutions_statuses_table.py
mutablesecurity/cli/__init__.py
mutablesecurity/cli/cli.py
mutablesecurity/cli/feedback_form.py
mutablesecurity/cli/messages.py
mutablesecurity/cli/printer.py
mutablesecurity/cli/solutions_manager_adapter.py
mutablesecurity/config/__init__.py
mutablesecurity/config/config.py
mutablesecurity/helpers/__init__.py
mutablesecurity/helpers/colors.py
mutablesecurity/helpers/data_type.py
mutablesecurity/helpers/exceptions.py
mutablesecurity/helpers/files.py
mutablesecurity/helpers/github.py
mutablesecurity/helpers/html.py
mutablesecurity/helpers/markdown.py
mutablesecurity/helpers/parsers.py
mutablesecurity/helpers/plain_yaml.py
mutablesecurity/helpers/pytest.py
mutablesecurity/helpers/python.py
mutablesecurity/helpers/type_hints.py
mutablesecurity/leader/__init__.py
mutablesecurity/leader/connections.py
mutablesecurity/leader/leader.py
mutablesecurity/logger/__init__.py
mutablesecurity/logger/logger.py
mutablesecurity/main/__init__.py
mutablesecurity/main/deployments.py
mutablesecurity/main/main.py
mutablesecurity/monitoring/__init__.py
mutablesecurity/monitoring/data_collection.py
mutablesecurity/monitoring/monitor.py
mutablesecurity/solutions/__init__.py
mutablesecurity/solutions/base/__init__.py
mutablesecurity/solutions/base/action.py
mutablesecurity/solutions/base/exception.py
mutablesecurity/solutions/base/information.py
mutablesecurity/solutions/base/log.py
mutablesecurity/solutions/base/object.py
mutablesecurity/solutions/base/result.py
mutablesecurity/solutions/base/solution.py
mutablesecurity/solutions/base/test.py
mutablesecurity/solutions/common/facts/bash.py
mutablesecurity/solutions/common/facts/files.py
mutablesecurity/solutions/common/facts/networking.py
mutablesecurity/solutions/common/facts/os.py
mutablesecurity/solutions/common/facts/process.py
mutablesecurity-0.4.0.dist-info/entry_points.txt
mutablesecurity-0.4.0.dist-info/LICENSE.md
mutablesecurity-0.4.0.dist-info/WHEEL
mutablesecurity-0.4.0.dist-info/METADATA
mutablesecurity-0.4.0.dist-info/RECORD
