Metadata-Version: 2.1
Name: mutablesecurity
Version: 0.4.0
Summary: Seamless deployment and management of cybersecurity solutions
Home-page: https://www.mutablesecurity.io
License: MIT
Keywords: cybersecurity,security-solutions,hardening,automatic-deployment
Author: MutableSecurity
Author-email: hello@mutablesecurity.io
Requires-Python: >=3.9,<4.0
Classifier: Environment :: Console
Classifier: License :: OSI Approved :: MIT License
Classifier: Operating System :: OS Independent
Classifier: Programming Language :: Python :: 3
Classifier: Programming Language :: Python :: 3.10
Classifier: Programming Language :: Python :: 3.9
Classifier: Topic :: Security
Classifier: Topic :: Software Development :: Libraries :: Python Modules
Classifier: Topic :: System :: Installation/Setup
Classifier: Topic :: System :: Monitoring
Classifier: Topic :: System :: Software Distribution
Requires-Dist: Click (>=8.0,<9.0)
Requires-Dist: PyYAML (==6.0)
Requires-Dist: humanfriendly (>=10.0,<11.0)
Requires-Dist: packaging (>=21.3,<22.0)
Requires-Dist: pyinfra (>=2.2,<3.0)
Requires-Dist: pypattyrn (>=1.2,<2.0)
Requires-Dist: requests (>=2.27.1,<3.0.0)
Requires-Dist: rich (==12.5.1)
Requires-Dist: sentry-sdk (>=1.9.8,<2.0.0)
Project-URL: Changelog, https://github.com/MutableSecurity/mutablesecurity/blob/main/CHANGELOG.md
Project-URL: Issue Tracker, https://github.com/MutableSecurity/mutablesecurity/issues
Project-URL: LinkedIn, https://www.linkedin.com/company/mutablesecurity
Project-URL: Repository, https://github.com/MutableSecurity/mutablesecurity
Project-URL: Twitter, https://twitter.com/mutablesecurity/
